<abstracts-retrieval-response xmlns="http://www.elsevier.com/xml/svapi/abstract/dtd" xmlns:dn="http://www.elsevier.com/xml/svapi/abstract/dtd" xmlns:ait="http://www.elsevier.com/xml/ani/ait" xmlns:ce="http://www.elsevier.com/xml/ani/common" xmlns:cto="http://www.elsevier.com/xml/cto/dtd" xmlns:dc="http://purl.org/dc/elements/1.1/" xmlns:prism="http://prismstandard.org/namespaces/basic/2.0/" xmlns:xocs="http://www.elsevier.com/xml/xocs/dtd" xmlns:xsi="http://www.w3.org/2001/XMLSchema-instance"><coredata><prism:url>https://api.elsevier.com/content/abstract/scopus_id/85064502751</prism:url><dc:identifier>SCOPUS_ID:85064502751</dc:identifier><eid>2-s2.0-85064502751</eid><prism:doi>10.1007/s10115-019-01361-2</prism:doi><dc:title>Automatic attribute construction for basketball modelling</dc:title><prism:aggregationType>Journal</prism:aggregationType><srctype>j</srctype><subtype>ar</subtype><subtypeDescription>Article</subtypeDescription><citedby-count>0</citedby-count><prism:publicationName>Knowledge and Information Systems</prism:publicationName><dc:publisher>
                        Springer London
                    </dc:publisher><source-id>15703</source-id><prism:issn>02193116 02191377</prism:issn><prism:coverDate>2019-01-01</prism:coverDate><openaccess>0</openaccess><openaccessFlag>false</openaccessFlag><dc:creator><author seq="1" auid="36976546800"><ce:initials>P.</ce:initials><ce:indexed-name>Vracar P.</ce:indexed-name><ce:surname>Vračar</ce:surname><ce:given-name>Petar</ce:given-name><preferred-name><ce:initials>P.</ce:initials><ce:indexed-name>Vračar P.</ce:indexed-name><ce:surname>Vračar</ce:surname><ce:given-name>Petar</ce:given-name></preferred-name><author-url>https://api.elsevier.com/content/author/author_id/36976546800</author-url><affiliation id="60031106" href="https://api.elsevier.com/content/affiliation/affiliation_id/60031106"/></author></dc:creator><dc:description><abstract xmlns="" original="y" xml:lang="eng">
                        <publishercopyright>© 2019, Springer-Verlag London Ltd., part of Springer Nature.</publishercopyright>
                        <ce:para>We address the problem of automatic extraction of patterns in the sequence of events in basketball games and construction of statistical models for generating a plausible simulation of a match between two distinct teams. We present a method for automatic construction of an attribute space which requires very little expert knowledge. The attributes are defined as the ratio between the number of entries and exits from higher-level concepts that are identified as groups of similar in-game events. The similarity between events is determined by the similarity between probability distributions describing the preceding and the following events in the observed sequences of game progression. The methodology is general and is applicable to any sports game that can be modelled as a random walk through the state space. Experiments on basketball show that automatically generated attributes are as informative as those derived using expert knowledge. Furthermore, the obtained simulations are in line with empirical data.</ce:para>
                    </abstract></dc:description><link href="https://api.elsevier.com/content/abstract/scopus_id/85064502751" rel="self"/><link href="https://www.scopus.com/inward/record.uri?partnerID=HzOxMe3b&amp;scp=85064502751&amp;origin=inward" rel="scopus"/><link href="https://www.scopus.com/inward/citedby.uri?partnerID=HzOxMe3b&amp;scp=85064502751&amp;origin=inward" rel="scopus-citedby"/></coredata><affiliation id="60031106" href="https://api.elsevier.com/content/affiliation/affiliation_id/60031106"><affilname>University of Ljubljana</affilname><affiliation-city>Ljubljana</affiliation-city><affiliation-country>Slovenia</affiliation-country></affiliation><authors><author seq="1" auid="36976546800"><ce:initials>P.</ce:initials><ce:indexed-name>Vracar P.</ce:indexed-name><ce:surname>Vračar</ce:surname><ce:given-name>Petar</ce:given-name><preferred-name><ce:initials>P.</ce:initials><ce:indexed-name>Vračar P.</ce:indexed-name><ce:surname>Vračar</ce:surname><ce:given-name>Petar</ce:given-name></preferred-name><author-url>https://api.elsevier.com/content/author/author_id/36976546800</author-url><affiliation id="60031106" href="https://api.elsevier.com/content/affiliation/affiliation_id/60031106"/></author><author seq="2" auid="57204664304"><ce:initials>E.</ce:initials><ce:indexed-name>Strumbelj E.</ce:indexed-name><ce:surname>Štrumbelj</ce:surname><ce:given-name>Erik</ce:given-name><preferred-name><ce:initials>E.</ce:initials><ce:indexed-name>Štrumbelj E.</ce:indexed-name><ce:surname>Štrumbelj</ce:surname><ce:given-name>Erik</ce:given-name></preferred-name><author-url>https://api.elsevier.com/content/author/author_id/57204664304</author-url><affiliation id="60031106" href="https://api.elsevier.com/content/affiliation/affiliation_id/60031106"/></author><author seq="3" auid="57188535146"><ce:initials>I.</ce:initials><ce:indexed-name>Kononenko I.</ce:indexed-name><ce:surname>Kononenko</ce:surname><ce:given-name>Igor</ce:given-name><preferred-name><ce:initials>I.</ce:initials><ce:indexed-name>Kononenko I.</ce:indexed-name><ce:surname>Kononenko</ce:surname><ce:given-name>Igor</ce:given-name></preferred-name><author-url>https://api.elsevier.com/content/author/author_id/57188535146</author-url><affiliation id="60031106" href="https://api.elsevier.com/content/affiliation/affiliation_id/60031106"/></author></authors><language xml:lang="eng"/><authkeywords><author-keyword>Attribute construction</author-keyword><author-keyword>Markov process</author-keyword><author-keyword>Match simulation</author-keyword><author-keyword>NBA</author-keyword><author-keyword>Sports modelling</author-keyword></authkeywords><idxterms/><subject-areas><subject-area code="1712" abbrev="COMP">Software</subject-area><subject-area code="1710" abbrev="COMP">Information Systems</subject-area><subject-area code="1709" abbrev="COMP">Human-Computer Interaction</subject-area><subject-area code="1708" abbrev="COMP">Hardware and Architecture</subject-area><subject-area code="1702" abbrev="COMP">Artificial Intelligence</subject-area></subject-areas><item xmlns=""><xocs:meta><xocs:funding-list has-funding-info="1" pui-match="primary"><xocs:funding-addon-generated-timestamp>2019-04-28T04:13:33.589Z</xocs:funding-addon-generated-timestamp><xocs:funding-addon-type>http://vtw.elsevier.com/data/voc/AddOnTypes/50.7/car</xocs:funding-addon-type></xocs:funding-list></xocs:meta><ait:process-info><ait:date-delivered day="25" month="04" timestamp="2019-04-25T16:10:51.000051-04:00" year="2019"/><ait:date-sort day="01" month="01" year="2019"/><ait:status stage="S200" state="new" type="core"/></ait:process-info><bibrecord><item-info><copyright type="Elsevier">Copyright 2019 Elsevier B.V., All rights reserved.</copyright><itemidlist>
                    <ce:doi>10.1007/s10115-019-01361-2</ce:doi>
                    <itemid idtype="PUI">627275766</itemid>
                    <itemid idtype="CAR-ID">916932171</itemid>
                    <itemid idtype="SCOPUS">20191104893</itemid>
                    <itemid idtype="SNCPX">2019044254</itemid>
                    <itemid idtype="SCP">85064502751</itemid>
                    <itemid idtype="SGR">85064502751</itemid>
                </itemidlist><history>
                    <date-created day="24" month="04" timestamp="BST 04:45:46" year="2019"/>
                </history><dbcollection>SCOPUS</dbcollection><dbcollection>SNCPX</dbcollection><dbcollection>Scopusbase</dbcollection></item-info><head><citation-info><citation-type code="ar"/><citation-language xml:lang="eng" language="English"/><abstract-language xml:lang="eng" language="English"/><author-keywords>
                        <author-keyword xml:lang="eng">Attribute construction</author-keyword>
                        <author-keyword xml:lang="eng">Markov process</author-keyword>
                        <author-keyword xml:lang="eng">Match simulation</author-keyword>
                        <author-keyword xml:lang="eng">NBA</author-keyword>
                        <author-keyword xml:lang="eng">Sports modelling</author-keyword>
                    </author-keywords></citation-info><citation-title><titletext original="y" xml:lang="eng" language="English">Automatic attribute construction for basketball modelling</titletext></citation-title><author-group><author auid="36976546800" orcid="0000-0003-1275-8057" seq="1" type="auth"><ce:initials>P.</ce:initials><ce:indexed-name>Vracar P.</ce:indexed-name><ce:surname>Vračar</ce:surname><ce:given-name>Petar</ce:given-name><preferred-name>
                            <ce:initials>P.</ce:initials>
                            <ce:indexed-name>Vračar P.</ce:indexed-name>
                            <ce:surname>Vračar</ce:surname>
                            <ce:given-name>Petar</ce:given-name>
                        </preferred-name></author><author auid="57204664304" seq="2" type="auth"><ce:initials>E.</ce:initials><ce:indexed-name>Strumbelj E.</ce:indexed-name><ce:surname>Štrumbelj</ce:surname><ce:given-name>Erik</ce:given-name><preferred-name>
                            <ce:initials>E.</ce:initials>
                            <ce:indexed-name>Štrumbelj E.</ce:indexed-name>
                            <ce:surname>Štrumbelj</ce:surname>
                            <ce:given-name>Erik</ce:given-name>
                        </preferred-name></author><author auid="57188535146" seq="3" type="auth"><ce:initials>I.</ce:initials><ce:indexed-name>Kononenko I.</ce:indexed-name><ce:surname>Kononenko</ce:surname><ce:given-name>Igor</ce:given-name><preferred-name>
                            <ce:initials>I.</ce:initials>
                            <ce:indexed-name>Kononenko I.</ce:indexed-name>
                            <ce:surname>Kononenko</ce:surname>
                            <ce:given-name>Igor</ce:given-name>
                        </preferred-name></author><affiliation afid="60031106" country="svn"><organization>Faculty of Computer and Information Science</organization><organization>University of Ljubljana</organization><address-part>Večna pot 113</address-part><city>Ljubljana</city><postal-code>1000</postal-code><affiliation-id afid="60031106"/><country>Slovenia</country></affiliation></author-group><correspondence><person>
                        <ce:initials>P.</ce:initials>
                        <ce:indexed-name>Vracar P.</ce:indexed-name>
                        <ce:surname>Vračar</ce:surname>
                        <ce:given-name>Petar</ce:given-name>
                    </person><affiliation country="svn"><organization>Faculty of Computer and Information Science</organization><organization>University of Ljubljana</organization><address-part>Večna pot 113</address-part><city>Ljubljana</city><postal-code>1000</postal-code><country>Slovenia</country></affiliation></correspondence><abstracts><abstract original="y" xml:lang="eng">
                        <publishercopyright>© 2019, Springer-Verlag London Ltd., part of Springer Nature.</publishercopyright>
                        <ce:para>We address the problem of automatic extraction of patterns in the sequence of events in basketball games and construction of statistical models for generating a plausible simulation of a match between two distinct teams. We present a method for automatic construction of an attribute space which requires very little expert knowledge. The attributes are defined as the ratio between the number of entries and exits from higher-level concepts that are identified as groups of similar in-game events. The similarity between events is determined by the similarity between probability distributions describing the preceding and the following events in the observed sequences of game progression. The methodology is general and is applicable to any sports game that can be modelled as a random walk through the state space. Experiments on basketball show that automatically generated attributes are as informative as those derived using expert knowledge. Furthermore, the obtained simulations are in line with empirical data.</ce:para>
                    </abstract></abstracts><source country="gbr" srcid="15703" type="j"><sourcetitle>Knowledge and Information Systems</sourcetitle><sourcetitle-abbrev>Knowl. Inf. Systems. Syst.</sourcetitle-abbrev><translated-sourcetitle xml:lang="eng">Knowledge and Information Systems</translated-sourcetitle><issn type="electronic">02193116</issn><issn type="print">02191377</issn><publicationyear first="2019"/><publicationdate>
                        <year>2019</year>
                    <date-text xfab-added="true">2019</date-text></publicationdate><website>
                        <ce:e-address type="email">http://www.springerlink.com/content/0219-1377</ce:e-address>
                    </website><publisher>
                        <publishername>Springer London</publishername>
                    </publisher></source><enhancement><classificationgroup><classifications type="ASJC">
                            <classification>1712</classification>
                            <classification>1710</classification>
                            <classification>1709</classification>
                            <classification>1708</classification>
                            <classification>1702</classification>
                        </classifications><classifications type="SUBJABBR"><classification>COMP</classification></classifications></classificationgroup></enhancement></head><tail><bibliography refcount="29">
                    <reference id="1">
                        <ref-info>
                            <ref-title>
                                <ref-titletext>Are the “four factors” indicators of one factor? an application of structural equation modeling methodology to NBA data in prediction of winning percentage</ref-titletext>
                            </ref-title>
                            <refd-itemidlist>
                                <itemid idtype="FRAGMENTID">CR1</itemid>
                                <itemid idtype="SGR">84859851626</itemid>
                            </refd-itemidlist>
                            <ref-authors>
                                <author seq="1">
                                    <ce:initials>T.</ce:initials>
                                    <ce:indexed-name>Baghal T.</ce:indexed-name>
                                    <ce:surname>Baghal</ce:surname>
                                </author>
                                <et-al/>
                            </ref-authors>
                            <ref-sourcetitle>J Quant Anal Sports</ref-sourcetitle>
                            <ref-publicationyear first="2012"/>
                            <ref-volisspag>
                                <voliss issue="1" volume="8"/>
                                <pagerange first="1" last="14"/>
                            </ref-volisspag>
                        </ref-info>
                        <ref-fulltext>Baghal T et al (2012) Are the “four factors” indicators of one factor? an application of structural equation modeling methodology to NBA data in prediction of winning percentage. J Quant Anal Sports 8(1):1–14</ref-fulltext>
                    </reference>
                    <reference id="2">
                        <ref-info>
                            <ref-title>
                                <ref-titletext>A simple measure of worker productivity in the national basketball association</ref-titletext>
                            </ref-title>
                            <refd-itemidlist>
                                <itemid idtype="FRAGMENTID">CR2</itemid>
                                <itemid idtype="SGR">70349469945</itemid>
                            </refd-itemidlist>
                            <ref-authors>
                                <author seq="1">
                                    <ce:initials>D.J.</ce:initials>
                                    <ce:indexed-name>Berri D.J.</ce:indexed-name>
                                    <ce:surname>Berri</ce:surname>
                                </author>
                            </ref-authors>
                            <ref-sourcetitle>Bus Sport</ref-sourcetitle>
                            <ref-publicationyear first="2008"/>
                            <ref-volisspag>
                                <voliss volume="3"/>
                                <pagerange first="1" last="40"/>
                            </ref-volisspag>
                        </ref-info>
                        <ref-fulltext>Berri DJ (2008) A simple measure of worker productivity in the national basketball association. Bus Sport 3:1–40</ref-fulltext>
                    </reference>
                    <reference id="3">
                        <ref-info>
                            <ref-title>
                                <ref-titletext>Verification of forecasts expressed in terms of probability</ref-titletext>
                            </ref-title>
                            <refd-itemidlist>
                                <itemid idtype="DOI">10.1175/1520-0493(1950)078&lt;0001:VOFEIT&gt;2.0.CO;2</itemid>
                                <itemid idtype="FRAGMENTID">CR3</itemid>
                                <itemid idtype="SGR">0003010182</itemid>
                            </refd-itemidlist>
                            <ref-authors>
                                <author seq="1">
                                    <ce:initials>G.W.</ce:initials>
                                    <ce:indexed-name>Brier G.W.</ce:indexed-name>
                                    <ce:surname>Brier</ce:surname>
                                </author>
                            </ref-authors>
                            <ref-sourcetitle>Mon Weather Rev</ref-sourcetitle>
                            <ref-publicationyear first="1950"/>
                            <ref-volisspag>
                                <voliss volume="75"/>
                                <pagerange first="1" last="3"/>
                            </ref-volisspag>
                        </ref-info>
                        <ref-fulltext>Brier GW (1950) Verification of forecasts expressed in terms of probability. Mon Weather Rev 75:1–3</ref-fulltext>
                    </reference>
                    <reference id="4">
                        <ref-info>
                            <ref-title>
                                <ref-titletext>A multiresolution stochastic process model for predicting basketball possession outcomes</ref-titletext>
                            </ref-title>
                            <refd-itemidlist>
                                <itemid idtype="DOI">10.1080/01621459.2016.1141685</itemid>
                                <itemid idtype="FRAGMENTID">CR4</itemid>
                                <itemid idtype="SGR">84983364705</itemid>
                            </refd-itemidlist>
                            <ref-authors>
                                <author seq="1">
                                    <ce:initials>D.</ce:initials>
                                    <ce:indexed-name>Cervone D.</ce:indexed-name>
                                    <ce:surname>Cervone</ce:surname>
                                </author>
                                <author seq="2">
                                    <ce:initials>A.</ce:initials>
                                    <ce:indexed-name>D'Amour A.</ce:indexed-name>
                                    <ce:surname>D’Amour</ce:surname>
                                </author>
                                <author seq="3">
                                    <ce:initials>L.</ce:initials>
                                    <ce:indexed-name>Bornn L.</ce:indexed-name>
                                    <ce:surname>Bornn</ce:surname>
                                </author>
                                <author seq="4">
                                    <ce:initials>K.</ce:initials>
                                    <ce:indexed-name>Goldsberry K.</ce:indexed-name>
                                    <ce:surname>Goldsberry</ce:surname>
                                </author>
                            </ref-authors>
                            <ref-sourcetitle>J Am Stat Assoc</ref-sourcetitle>
                            <ref-publicationyear first="2016"/>
                            <ref-volisspag>
                                <voliss issue="514" volume="111"/>
                                <pagerange first="585" last="599"/>
                            </ref-volisspag>
                        </ref-info>
                        <ref-fulltext>Cervone D, D’Amour A, Bornn L, Goldsberry K (2016) A multiresolution stochastic process model for predicting basketball possession outcomes. J Am Stat Assoc 111(514):585–599</ref-fulltext>
                    </reference>
                    <reference id="5">
                        <ref-info>
                            <ref-title>
                                <ref-titletext>Comprehensive survey on distance/similarity measures between probability density functions</ref-titletext>
                            </ref-title>
                            <refd-itemidlist>
                                <itemid idtype="FRAGMENTID">CR5</itemid>
                                <itemid idtype="SGR">70349266356</itemid>
                            </refd-itemidlist>
                            <ref-authors>
                                <author seq="1">
                                    <ce:initials>S.-H.</ce:initials>
                                    <ce:indexed-name>Cha S.-H.</ce:indexed-name>
                                    <ce:surname>Cha</ce:surname>
                                </author>
                            </ref-authors>
                            <ref-sourcetitle>City</ref-sourcetitle>
                            <ref-publicationyear first="2007"/>
                            <ref-volisspag>
                                <voliss volume="1"/>
                                <pagerange first="1"/>
                            </ref-volisspag>
                        </ref-info>
                        <ref-fulltext>Cha S-H (2007) Comprehensive survey on distance/similarity measures between probability density functions. City 1:1</ref-fulltext>
                    </reference>
                    <reference id="6">
                        <ref-info>
                            <ref-title>
                                <ref-titletext>Quantifying shot quality in the nba</ref-titletext>
                            </ref-title>
                            <refd-itemidlist>
                                <itemid idtype="FRAGMENTID">CR6</itemid>
                                <itemid idtype="SGR">85020249799</itemid>
                            </refd-itemidlist>
                            <ref-authors>
                                <author seq="1">
                                    <ce:initials>Y.-H.</ce:initials>
                                    <ce:indexed-name>Chang Y.-H.</ce:indexed-name>
                                    <ce:surname>Chang</ce:surname>
                                </author>
                                <author seq="2">
                                    <ce:initials>R.</ce:initials>
                                    <ce:indexed-name>Maheswaran R.</ce:indexed-name>
                                    <ce:surname>Maheswaran</ce:surname>
                                </author>
                                <author seq="3">
                                    <ce:initials>J.</ce:initials>
                                    <ce:indexed-name>Su J.</ce:indexed-name>
                                    <ce:surname>Su</ce:surname>
                                </author>
                                <author seq="4">
                                    <ce:initials>S.</ce:initials>
                                    <ce:indexed-name>Kwok S.</ce:indexed-name>
                                    <ce:surname>Kwok</ce:surname>
                                </author>
                                <author seq="5">
                                    <ce:initials>T.</ce:initials>
                                    <ce:indexed-name>Levy T.</ce:indexed-name>
                                    <ce:surname>Levy</ce:surname>
                                </author>
                                <author seq="6">
                                    <ce:initials>A.</ce:initials>
                                    <ce:indexed-name>Wexler A.</ce:indexed-name>
                                    <ce:surname>Wexler</ce:surname>
                                </author>
                                <author seq="7">
                                    <ce:initials>K.</ce:initials>
                                    <ce:indexed-name>Squire K.</ce:indexed-name>
                                    <ce:surname>Squire</ce:surname>
                                </author>
                            </ref-authors>
                            <ref-sourcetitle>Proceedings of the 8Th Annual MIT Sloan Sports Analytics Conference</ref-sourcetitle>
                            <ref-publicationyear first="2014"/>
                            <ref-text>MIT, Boston</ref-text>
                        </ref-info>
                        <ref-fulltext>Chang Y-H, Maheswaran R, Su J, Kwok S, Levy T, Wexler A, Squire K (2014) Quantifying shot quality in the nba. In: Proceedings of the 8th annual MIT sloan sports analytics conference. MIT, Boston</ref-fulltext>
                    </reference>
                    <reference id="7">
                        <ref-info>
                            <ref-title>
                                <ref-titletext>Classification of passes in football matches using spatiotemporal data</ref-titletext>
                            </ref-title>
                            <refd-itemidlist>
                                <itemid idtype="FRAGMENTID">CR7</itemid>
                                <itemid idtype="SGR">85045544550</itemid>
                            </refd-itemidlist>
                            <ref-authors>
                                <author seq="1">
                                    <ce:initials>S.</ce:initials>
                                    <ce:indexed-name>Chawla S.</ce:indexed-name>
                                    <ce:surname>Chawla</ce:surname>
                                </author>
                                <author seq="2">
                                    <ce:initials>J.</ce:initials>
                                    <ce:indexed-name>Estephan J.</ce:indexed-name>
                                    <ce:surname>Estephan</ce:surname>
                                </author>
                                <author seq="3">
                                    <ce:initials>J.</ce:initials>
                                    <ce:indexed-name>Gudmundsson J.</ce:indexed-name>
                                    <ce:surname>Gudmundsson</ce:surname>
                                </author>
                                <author seq="4">
                                    <ce:initials>M.</ce:initials>
                                    <ce:indexed-name>Horton M.</ce:indexed-name>
                                    <ce:surname>Horton</ce:surname>
                                </author>
                            </ref-authors>
                            <ref-sourcetitle>ACM Trans Spat Algorithms Syst</ref-sourcetitle>
                            <ref-publicationyear first="2017"/>
                            <ref-volisspag>
                                <voliss volume="3"/>
                                <pagerange first="6"/>
                            </ref-volisspag>
                        </ref-info>
                        <ref-fulltext>Chawla S, Estephan J, Gudmundsson J, Horton M (2017) Classification of passes in football matches using spatiotemporal data. ACM Trans Spat Algorithms Syst 3:6</ref-fulltext>
                    </reference>
                    <reference id="8">
                        <ref-info>
                            <ref-title>
                                <ref-titletext>The harsh rule of the goals: Data-driven performance indicators for football teams</ref-titletext>
                            </ref-title>
                            <refd-itemidlist>
                                <itemid idtype="FRAGMENTID">CR8</itemid>
                                <itemid idtype="SGR">84962915609</itemid>
                            </refd-itemidlist>
                            <ref-authors>
                                <author seq="1">
                                    <ce:initials>P.</ce:initials>
                                    <ce:indexed-name>Cintia P.</ce:indexed-name>
                                    <ce:surname>Cintia</ce:surname>
                                </author>
                                <author seq="2">
                                    <ce:initials>F.</ce:initials>
                                    <ce:indexed-name>Giannotti F.</ce:indexed-name>
                                    <ce:surname>Giannotti</ce:surname>
                                </author>
                                <author seq="3">
                                    <ce:initials>L.</ce:initials>
                                    <ce:indexed-name>Pappalardo L.</ce:indexed-name>
                                    <ce:surname>Pappalardo</ce:surname>
                                </author>
                                <author seq="4">
                                    <ce:initials>D.</ce:initials>
                                    <ce:indexed-name>Pedreschi D.</ce:indexed-name>
                                    <ce:surname>Pedreschi</ce:surname>
                                </author>
                                <author seq="5">
                                    <ce:initials>M.</ce:initials>
                                    <ce:indexed-name>Malvaldi M.</ce:indexed-name>
                                    <ce:surname>Malvaldi</ce:surname>
                                </author>
                            </ref-authors>
                            <ref-sourcetitle>2015 IEEE International Conference on Data Science and Advanced Analytics (DSAA), IEEE</ref-sourcetitle>
                            <ref-publicationyear first="2015"/>
                            <ref-volisspag>
                                <voliss volume="36678"/>
                                <pagerange first="1" last="10"/>
                            </ref-volisspag>
                        </ref-info>
                        <ref-fulltext>Cintia P, Giannotti F, Pappalardo L, Pedreschi D, Malvaldi M (2015) The harsh rule of the goals: Data-driven performance indicators for football teams. In: 2015 IEEE international conference on data science and advanced analytics (DSAA), IEEE, 36678 pp. 1–10</ref-fulltext>
                    </reference>
                    <reference id="9">
                        <ref-info>
                            <refd-itemidlist>
                                <itemid idtype="DOI">10.1007/978-3-319-25855-3</itemid>
                                <itemid idtype="FRAGMENTID">CR9</itemid>
                                <itemid idtype="SGR">84994178198</itemid>
                            </refd-itemidlist>
                            <ref-authors>
                                <author seq="1">
                                    <ce:initials>F.M.</ce:initials>
                                    <ce:indexed-name>Clemente F.M.</ce:indexed-name>
                                    <ce:surname>Clemente</ce:surname>
                                </author>
                                <author seq="2">
                                    <ce:initials>F.M.L.</ce:initials>
                                    <ce:indexed-name>Martins F.M.L.</ce:indexed-name>
                                    <ce:surname>Martins</ce:surname>
                                </author>
                                <author seq="3">
                                    <ce:initials>R.S.</ce:initials>
                                    <ce:indexed-name>Mendes R.S.</ce:indexed-name>
                                    <ce:surname>Mendes</ce:surname>
                                </author>
                                <et-al/>
                            </ref-authors>
                            <ref-sourcetitle>Social network analysis applied to team sports analysis</ref-sourcetitle>
                            <ref-publicationyear first="2016"/>
                            <ref-text>Springer, Berlin</ref-text>
                        </ref-info>
                        <ref-fulltext>Clemente FM, Martins FML, Mendes RS et al (2016) Social network analysis applied to team sports analysis. Springer, Berlin</ref-fulltext>
                    </reference>
                    <reference id="10">
                        <ref-info>
                            <ref-title>
                                <ref-titletext>New USCF rating system</ref-titletext>
                            </ref-title>
                            <refd-itemidlist>
                                <itemid idtype="FRAGMENTID">CR10</itemid>
                                <itemid idtype="SGR">0004744054</itemid>
                            </refd-itemidlist>
                            <ref-authors>
                                <author seq="1">
                                    <ce:initials>A.</ce:initials>
                                    <ce:indexed-name>Elo A.</ce:indexed-name>
                                    <ce:surname>Elo</ce:surname>
                                </author>
                            </ref-authors>
                            <ref-sourcetitle>Chess life</ref-sourcetitle>
                            <ref-publicationyear first="1961"/>
                            <ref-volisspag>
                                <voliss volume="16"/>
                                <pagerange first="160" last="161"/>
                            </ref-volisspag>
                        </ref-info>
                        <ref-fulltext>Elo A (1961) New USCF rating system. Chess life 16:160–161</ref-fulltext>
                    </reference>
                    <reference id="11">
                        <ref-info>
                            <ref-title>
                                <ref-titletext>A scoring system for probability forecast of ranked categories</ref-titletext>
                            </ref-title>
                            <refd-itemidlist>
                                <itemid idtype="DOI">10.1175/1520-0450(1969)008&lt;0985:ASSFPF&gt;2.0.CO;2</itemid>
                                <itemid idtype="FRAGMENTID">CR11</itemid>
                                <itemid idtype="SGR">0000165587</itemid>
                            </refd-itemidlist>
                            <ref-authors>
                                <author seq="1">
                                    <ce:initials>E.S.</ce:initials>
                                    <ce:indexed-name>Epstein E.S.</ce:indexed-name>
                                    <ce:surname>Epstein</ce:surname>
                                </author>
                            </ref-authors>
                            <ref-sourcetitle>J Appl Meteorol</ref-sourcetitle>
                            <ref-publicationyear first="1969"/>
                            <ref-volisspag>
                                <voliss volume="8"/>
                                <pagerange first="985" last="987"/>
                            </ref-volisspag>
                        </ref-info>
                        <ref-fulltext>Epstein ES (1969) A scoring system for probability forecast of ranked categories. J Appl Meteorol 8:985–987</ref-fulltext>
                    </reference>
                    <reference id="12">
                        <ref-info>
                            <ref-title>
                                <ref-titletext>Characterizing the spatial structure of defensive skill in professional basketball</ref-titletext>
                            </ref-title>
                            <refd-itemidlist>
                                <itemid idtype="DOI">10.1214/14-AOAS799</itemid>
                                <itemid idtype="FRAGMENTID">CR12</itemid>
                                <itemid idtype="SGR">84929667416</itemid>
                            </refd-itemidlist>
                            <ref-authors>
                                <author seq="1">
                                    <ce:initials>A.</ce:initials>
                                    <ce:indexed-name>Franks A.</ce:indexed-name>
                                    <ce:surname>Franks</ce:surname>
                                </author>
                                <author seq="2">
                                    <ce:initials>A.</ce:initials>
                                    <ce:indexed-name>Miller A.</ce:indexed-name>
                                    <ce:surname>Miller</ce:surname>
                                </author>
                                <author seq="3">
                                    <ce:initials>L.</ce:initials>
                                    <ce:indexed-name>Bornn L.</ce:indexed-name>
                                    <ce:surname>Bornn</ce:surname>
                                </author>
                                <author seq="4">
                                    <ce:initials>K.</ce:initials>
                                    <ce:indexed-name>Goldsberry K.</ce:indexed-name>
                                    <ce:surname>Goldsberry</ce:surname>
                                </author>
                                <et-al/>
                            </ref-authors>
                            <ref-sourcetitle>Annal Appl Stat</ref-sourcetitle>
                            <ref-publicationyear first="2015"/>
                            <ref-volisspag>
                                <voliss volume="9"/>
                                <pagerange first="94" last="121"/>
                            </ref-volisspag>
                        </ref-info>
                        <ref-fulltext>Franks A, Miller A, Bornn L, Goldsberry K et al (2015) Characterizing the spatial structure of defensive skill in professional basketball. Annal Appl Stat 9:94–121</ref-fulltext>
                    </reference>
                    <reference id="13">
                        <ref-info>
                            <ref-title>
                                <ref-titletext>Random walk picture of basketball scoring</ref-titletext>
                            </ref-title>
                            <refd-itemidlist>
                                <itemid idtype="FRAGMENTID">CR13</itemid>
                                <itemid idtype="SGR">84859820457</itemid>
                            </refd-itemidlist>
                            <ref-authors>
                                <author seq="1">
                                    <ce:initials>A.</ce:initials>
                                    <ce:indexed-name>Gabel A.</ce:indexed-name>
                                    <ce:surname>Gabel</ce:surname>
                                </author>
                                <author seq="2">
                                    <ce:initials>S.</ce:initials>
                                    <ce:indexed-name>Redner S.</ce:indexed-name>
                                    <ce:surname>Redner</ce:surname>
                                </author>
                                <et-al/>
                            </ref-authors>
                            <ref-sourcetitle>J Quant Anal Sports</ref-sourcetitle>
                            <ref-publicationyear first="2012"/>
                            <ref-volisspag>
                                <voliss issue="1" volume="8"/>
                                <pagerange first="1" last="18"/>
                            </ref-volisspag>
                        </ref-info>
                        <ref-fulltext>Gabel A, Redner S et al (2012) Random walk picture of basketball scoring. J Quant Anal Sports 8(1):1–18</ref-fulltext>
                    </reference>
                    <reference id="14">
                        <ref-info>
                            <ref-title>
                                <ref-titletext>Rational decisions</ref-titletext>
                            </ref-title>
                            <refd-itemidlist>
                                <itemid idtype="FRAGMENTID">CR14</itemid>
                                <itemid idtype="SGR">0000558731</itemid>
                            </refd-itemidlist>
                            <ref-authors>
                                <author seq="1">
                                    <ce:initials>I.J.</ce:initials>
                                    <ce:indexed-name>Good I.J.</ce:indexed-name>
                                    <ce:surname>Good</ce:surname>
                                </author>
                            </ref-authors>
                            <ref-sourcetitle>J R Stat Soc Series B (Methodological)</ref-sourcetitle>
                            <ref-publicationyear first="1952"/>
                            <ref-volisspag>
                                <pagerange first="107" last="114"/>
                            </ref-volisspag>
                        </ref-info>
                        <ref-fulltext>Good IJ (1952) Rational decisions. J R Stat Soc Series B (Methodological), pp 107–114</ref-fulltext>
                    </reference>
                    <reference id="15">
                        <ref-info>
                            <ref-title>
                                <ref-titletext>Spatio-temporal analysis of team sports</ref-titletext>
                            </ref-title>
                            <refd-itemidlist>
                                <itemid idtype="DOI">10.1145/3054132</itemid>
                                <itemid idtype="FRAGMENTID">CR15</itemid>
                                <itemid idtype="SGR">85017457869</itemid>
                            </refd-itemidlist>
                            <ref-authors>
                                <author seq="1">
                                    <ce:initials>J.</ce:initials>
                                    <ce:indexed-name>Gudmundsson J.</ce:indexed-name>
                                    <ce:surname>Gudmundsson</ce:surname>
                                </author>
                                <author seq="2">
                                    <ce:initials>M.</ce:initials>
                                    <ce:indexed-name>Horton M.</ce:indexed-name>
                                    <ce:surname>Horton</ce:surname>
                                </author>
                            </ref-authors>
                            <ref-sourcetitle>ACM Comput Surv</ref-sourcetitle>
                            <ref-publicationyear first="2017"/>
                            <ref-volisspag>
                                <voliss volume="50"/>
                                <pagerange first="22"/>
                            </ref-volisspag>
                        </ref-info>
                        <ref-fulltext>Gudmundsson J, Horton M (2017) Spatio-temporal analysis of team sports. ACM Comput Surv 50:22</ref-fulltext>
                    </reference>
                    <reference id="16">
                        <ref-info>
                            <refd-itemidlist>
                                <itemid idtype="FRAGMENTID">CR16</itemid>
                                <itemid idtype="SGR">26244468244</itemid>
                            </refd-itemidlist>
                            <ref-authors>
                                <author seq="1">
                                    <ce:initials>J.</ce:initials>
                                    <ce:indexed-name>Hollinger J.</ce:indexed-name>
                                    <ce:surname>Hollinger</ce:surname>
                                </author>
                            </ref-authors>
                            <ref-sourcetitle>Pro Basketball Prospectus 2003–2004</ref-sourcetitle>
                            <ref-publicationyear first="2003"/>
                            <ref-text>Brassey’s, San Francisco</ref-text>
                        </ref-info>
                        <ref-fulltext>Hollinger J (2003) Pro Basketball Prospectus 2003–2004. Brassey’s, San Francisco</ref-fulltext>
                    </reference>
                    <reference id="17">
                        <ref-info>
                            <ref-title>
                                <ref-titletext>Using ELO ratings for match result prediction in association football</ref-titletext>
                            </ref-title>
                            <refd-itemidlist>
                                <itemid idtype="DOI">10.1016/j.ijforecast.2009.10.002</itemid>
                                <itemid idtype="FRAGMENTID">CR17</itemid>
                                <itemid idtype="SGR">77952292589</itemid>
                            </refd-itemidlist>
                            <ref-authors>
                                <author seq="1">
                                    <ce:initials>L.M.</ce:initials>
                                    <ce:indexed-name>Hvattum L.M.</ce:indexed-name>
                                    <ce:surname>Hvattum</ce:surname>
                                </author>
                                <author seq="2">
                                    <ce:initials>H.</ce:initials>
                                    <ce:indexed-name>Arntzen H.</ce:indexed-name>
                                    <ce:surname>Arntzen</ce:surname>
                                </author>
                            </ref-authors>
                            <ref-sourcetitle>Int J Forecast</ref-sourcetitle>
                            <ref-publicationyear first="2010"/>
                            <ref-volisspag>
                                <voliss volume="26"/>
                                <pagerange first="460" last="470"/>
                            </ref-volisspag>
                        </ref-info>
                        <ref-fulltext>Hvattum LM, Arntzen H (2010) Using ELO ratings for match result prediction in association football. Int J Forecast 26:460–470</ref-fulltext>
                    </reference>
                    <reference id="18">
                        <ref-info>
                            <ref-title>
                                <ref-titletext>On biases in estimating multi-valued attributes</ref-titletext>
                            </ref-title>
                            <refd-itemidlist>
                                <itemid idtype="FRAGMENTID">CR18</itemid>
                                <itemid idtype="SGR">0001796836</itemid>
                            </refd-itemidlist>
                            <ref-authors>
                                <author seq="1">
                                    <ce:initials>I.</ce:initials>
                                    <ce:indexed-name>Kononenko I.</ce:indexed-name>
                                    <ce:surname>Kononenko</ce:surname>
                                </author>
                            </ref-authors>
                            <ref-sourcetitle>In: Ijcai</ref-sourcetitle>
                            <ref-publicationyear first="1995"/>
                            <ref-volisspag>
                                <voliss volume="95"/>
                                <pagerange first="1034" last="1040"/>
                            </ref-volisspag>
                        </ref-info>
                        <ref-fulltext>Kononenko I (1995) On biases in estimating multi-valued attributes. In: Ijcai. 95: 1034–1040</ref-fulltext>
                    </reference>
                    <reference id="19">
                        <ref-info>
                            <ref-title>
                                <ref-titletext>A starting point for analyzing basketball statistics</ref-titletext>
                            </ref-title>
                            <refd-itemidlist>
                                <itemid idtype="FRAGMENTID">CR19</itemid>
                                <itemid idtype="SGR">56749120908</itemid>
                            </refd-itemidlist>
                            <ref-authors>
                                <author seq="1">
                                    <ce:initials>J.</ce:initials>
                                    <ce:indexed-name>Kubatko J.</ce:indexed-name>
                                    <ce:surname>Kubatko</ce:surname>
                                </author>
                                <author seq="2">
                                    <ce:initials>D.</ce:initials>
                                    <ce:indexed-name>Oliver D.</ce:indexed-name>
                                    <ce:surname>Oliver</ce:surname>
                                </author>
                                <author seq="3">
                                    <ce:initials>K.</ce:initials>
                                    <ce:indexed-name>Pelton K.</ce:indexed-name>
                                    <ce:surname>Pelton</ce:surname>
                                </author>
                                <author seq="4">
                                    <ce:initials>D.T.</ce:initials>
                                    <ce:indexed-name>Rosenbaum D.T.</ce:indexed-name>
                                    <ce:surname>Rosenbaum</ce:surname>
                                </author>
                            </ref-authors>
                            <ref-sourcetitle>J Quant Anal Sports</ref-sourcetitle>
                            <ref-publicationyear first="2007"/>
                            <ref-volisspag>
                                <voliss volume="3"/>
                                <pagerange first="1" last="22"/>
                            </ref-volisspag>
                        </ref-info>
                        <ref-fulltext>Kubatko J, Oliver D, Pelton K, Rosenbaum DT (2007) A starting point for analyzing basketball statistics. J Quant Anal Sports 3:1–22</ref-fulltext>
                    </reference>
                    <reference id="20">
                        <ref-info>
                            <ref-title>
                                <ref-titletext>On information and sufficiency</ref-titletext>
                            </ref-title>
                            <refd-itemidlist>
                                <itemid idtype="DOI">10.1214/aoms/1177729694</itemid>
                                <itemid idtype="FRAGMENTID">CR20</itemid>
                                <itemid idtype="SGR">0001927585</itemid>
                            </refd-itemidlist>
                            <ref-authors>
                                <author seq="1">
                                    <ce:initials>S.</ce:initials>
                                    <ce:indexed-name>Kullback S.</ce:indexed-name>
                                    <ce:surname>Kullback</ce:surname>
                                </author>
                                <author seq="2">
                                    <ce:initials>R.A.</ce:initials>
                                    <ce:indexed-name>Leibler R.A.</ce:indexed-name>
                                    <ce:surname>Leibler</ce:surname>
                                </author>
                            </ref-authors>
                            <ref-sourcetitle>Annal Math Stat</ref-sourcetitle>
                            <ref-publicationyear first="1951"/>
                            <ref-volisspag>
                                <voliss volume="22"/>
                                <pagerange first="79" last="86"/>
                            </ref-volisspag>
                        </ref-info>
                        <ref-fulltext>Kullback S, Leibler RA (1951) On information and sufficiency. Annal Math Stat 22:79–86</ref-fulltext>
                    </reference>
                    <reference id="21">
                        <ref-info>
                            <refd-itemidlist>
                                <itemid idtype="FRAGMENTID">CR21</itemid>
                                <itemid idtype="SGR">84872109644</itemid>
                            </refd-itemidlist>
                            <ref-authors>
                                <author seq="1">
                                    <ce:initials>A.N.</ce:initials>
                                    <ce:indexed-name>Langville A.N.</ce:indexed-name>
                                    <ce:surname>Langville</ce:surname>
                                </author>
                                <author seq="2">
                                    <ce:initials>C.D.</ce:initials>
                                    <ce:indexed-name>Meyer C.D.</ce:indexed-name>
                                    <ce:surname>Meyer</ce:surname>
                                </author>
                            </ref-authors>
                            <ref-sourcetitle>Who’s# 1?: the science of rating and ranking</ref-sourcetitle>
                            <ref-publicationyear first="2012"/>
                            <ref-text>Princeton University Press, Princeton</ref-text>
                        </ref-info>
                        <ref-fulltext>Langville AN, Meyer CD (2012) Who’s# 1?: the science of rating and ranking. Princeton University Press, Princeton</ref-fulltext>
                    </reference>
                    <reference id="22">
                        <ref-info>
                            <ref-title>
                                <ref-titletext>Data-driven ghosting using deep imitation learning</ref-titletext>
                            </ref-title>
                            <refd-itemidlist>
                                <itemid idtype="FRAGMENTID">CR22</itemid>
                                <itemid idtype="SGR">85035801578</itemid>
                            </refd-itemidlist>
                            <ref-authors>
                                <author seq="1">
                                    <ce:initials>H.M.</ce:initials>
                                    <ce:indexed-name>Le H.M.</ce:indexed-name>
                                    <ce:surname>Le</ce:surname>
                                </author>
                                <author seq="2">
                                    <ce:initials>P.</ce:initials>
                                    <ce:indexed-name>Carr P.</ce:indexed-name>
                                    <ce:surname>Carr</ce:surname>
                                </author>
                                <author seq="3">
                                    <ce:initials>Y.</ce:initials>
                                    <ce:indexed-name>Yue Y.</ce:indexed-name>
                                    <ce:surname>Yue</ce:surname>
                                </author>
                                <author seq="4">
                                    <ce:initials>P.</ce:initials>
                                    <ce:indexed-name>Lucey P.</ce:indexed-name>
                                    <ce:surname>Lucey</ce:surname>
                                </author>
                            </ref-authors>
                            <ref-sourcetitle>2017 MIT Sloan Sports Analytics Conference</ref-sourcetitle>
                            <ref-publicationyear first="2017"/>
                        </ref-info>
                        <ref-fulltext>Le HM, Carr P, Yue Y, Lucey P (2017) Data-driven ghosting using deep imitation learning. In: 2017 MIT sloan sports analytics conference</ref-fulltext>
                    </reference>
                    <reference id="23">
                        <ref-info>
                            <ref-title>
                                <ref-titletext>Quality vs quantity: Improved shot prediction in soccer using strategic features from spatiotemporal data</ref-titletext>
                            </ref-title>
                            <refd-itemidlist>
                                <itemid idtype="FRAGMENTID">CR23</itemid>
                                <itemid idtype="SGR">85017421258</itemid>
                            </refd-itemidlist>
                            <ref-authors>
                                <author seq="1">
                                    <ce:initials>P.</ce:initials>
                                    <ce:indexed-name>Lucey P.</ce:indexed-name>
                                    <ce:surname>Lucey</ce:surname>
                                </author>
                                <author seq="2">
                                    <ce:initials>A.</ce:initials>
                                    <ce:indexed-name>Bialkowski A.</ce:indexed-name>
                                    <ce:surname>Bialkowski</ce:surname>
                                </author>
                                <author seq="3">
                                    <ce:initials>M.</ce:initials>
                                    <ce:indexed-name>Monfort M.</ce:indexed-name>
                                    <ce:surname>Monfort</ce:surname>
                                </author>
                                <author seq="4">
                                    <ce:initials>P.</ce:initials>
                                    <ce:indexed-name>Carr P.</ce:indexed-name>
                                    <ce:surname>Carr</ce:surname>
                                </author>
                                <author seq="5">
                                    <ce:initials>I.</ce:initials>
                                    <ce:indexed-name>Matthews I.</ce:indexed-name>
                                    <ce:surname>Matthews</ce:surname>
                                </author>
                            </ref-authors>
                            <ref-sourcetitle>Proceedings of the 8Th Annual MIT Sloan Sports Analytics Conference</ref-sourcetitle>
                            <ref-publicationyear first="2014"/>
                            <ref-volisspag>
                                <pagerange first="1" last="9"/>
                            </ref-volisspag>
                        </ref-info>
                        <ref-fulltext>Lucey P, Bialkowski A, Monfort M, Carr P, Matthews I (2014) Quality vs quantity: improved shot prediction in soccer using strategic features from spatiotemporal data. In: Proceedings of the 8th annual MIT sloan sports analytics conference. pp 1–9</ref-fulltext>
                    </reference>
                    <reference id="24">
                        <ref-info>
                            <ref-title>
                                <ref-titletext>Deep learning of player trajectory representations for team activity analysis</ref-titletext>
                            </ref-title>
                            <refd-itemidlist>
                                <itemid idtype="FRAGMENTID">CR24</itemid>
                                <itemid idtype="SGR">85058052464</itemid>
                            </refd-itemidlist>
                            <ref-authors>
                                <author seq="1">
                                    <ce:initials>N.</ce:initials>
                                    <ce:indexed-name>Mehrasa N.</ce:indexed-name>
                                    <ce:surname>Mehrasa</ce:surname>
                                </author>
                                <author seq="2">
                                    <ce:initials>Y.</ce:initials>
                                    <ce:indexed-name>Zhong Y.</ce:indexed-name>
                                    <ce:surname>Zhong</ce:surname>
                                </author>
                                <author seq="3">
                                    <ce:initials>F.</ce:initials>
                                    <ce:indexed-name>Tung F.</ce:indexed-name>
                                    <ce:surname>Tung</ce:surname>
                                </author>
                                <author seq="4">
                                    <ce:initials>L.</ce:initials>
                                    <ce:indexed-name>Bornn L.</ce:indexed-name>
                                    <ce:surname>Bornn</ce:surname>
                                </author>
                                <author seq="5">
                                    <ce:initials>G.</ce:initials>
                                    <ce:indexed-name>Mori G.</ce:indexed-name>
                                    <ce:surname>Mori</ce:surname>
                                </author>
                            </ref-authors>
                            <ref-sourcetitle>2018 MIT Sloan Sports Analytics Conference</ref-sourcetitle>
                            <ref-publicationyear first="2018"/>
                        </ref-info>
                        <ref-fulltext>Mehrasa N, Zhong Y, Tung F, Bornn L, Mori G (2018) Deep learning of player trajectory representations for team activity analysis. In: 2018 MIT sloan sports analytics conference</ref-fulltext>
                    </reference>
                    <reference id="25">
                        <ref-info>
                            <refd-itemidlist>
                                <itemid idtype="FRAGMENTID">CR25</itemid>
                                <itemid idtype="SGR">14644411920</itemid>
                            </refd-itemidlist>
                            <ref-authors>
                                <author seq="1">
                                    <ce:initials>D.</ce:initials>
                                    <ce:indexed-name>Oliver D.</ce:indexed-name>
                                    <ce:surname>Oliver</ce:surname>
                                </author>
                            </ref-authors>
                            <ref-sourcetitle>Basketball on paper: rules and tools for performance analysis</ref-sourcetitle>
                            <ref-publicationyear first="2004"/>
                            <ref-text>Potomac Books Inc, Potomac</ref-text>
                        </ref-info>
                        <ref-fulltext>Oliver D (2004) Basketball on paper: rules and tools for performance analysis. Potomac Books Inc, Potomac</ref-fulltext>
                    </reference>
                    <reference id="26">
                        <ref-info>
                            <ref-title>
                                <ref-titletext>Silhouettes: a graphical aid to the interpretation and validation of cluster analysis</ref-titletext>
                            </ref-title>
                            <refd-itemidlist>
                                <itemid idtype="DOI">10.1016/0377-0427(87)90125-7</itemid>
                                <itemid idtype="FRAGMENTID">CR26</itemid>
                                <itemid idtype="SGR">0023453329</itemid>
                            </refd-itemidlist>
                            <ref-authors>
                                <author seq="1">
                                    <ce:initials>P.J.</ce:initials>
                                    <ce:indexed-name>Rousseeuw P.J.</ce:indexed-name>
                                    <ce:surname>Rousseeuw</ce:surname>
                                </author>
                            </ref-authors>
                            <ref-sourcetitle>J Comput Appl Math</ref-sourcetitle>
                            <ref-publicationyear first="1987"/>
                            <ref-volisspag>
                                <voliss volume="20"/>
                                <pagerange first="53" last="65"/>
                            </ref-volisspag>
                        </ref-info>
                        <ref-fulltext>Rousseeuw PJ (1987) Silhouettes: a graphical aid to the interpretation and validation of cluster analysis. J Comput Appl Math 20:53–65</ref-fulltext>
                    </reference>
                    <reference id="27">
                        <ref-info>
                            <ref-title>
                                <ref-titletext>Simulating a basketball match with a homogeneous Markov model and forecasting the outcome</ref-titletext>
                            </ref-title>
                            <refd-itemidlist>
                                <itemid idtype="DOI">10.1016/j.ijforecast.2011.01.004</itemid>
                                <itemid idtype="FRAGMENTID">CR27</itemid>
                                <itemid idtype="SGR">84856693809</itemid>
                            </refd-itemidlist>
                            <ref-authors>
                                <author seq="1">
                                    <ce:initials>E.</ce:initials>
                                    <ce:indexed-name>Strumbelj E.</ce:indexed-name>
                                    <ce:surname>Štrumbelj</ce:surname>
                                </author>
                                <author seq="2">
                                    <ce:initials>P.</ce:initials>
                                    <ce:indexed-name>Vracar P.</ce:indexed-name>
                                    <ce:surname>Vračar</ce:surname>
                                </author>
                            </ref-authors>
                            <ref-sourcetitle>Int J Forecast</ref-sourcetitle>
                            <ref-publicationyear first="2012"/>
                            <ref-volisspag>
                                <voliss volume="28"/>
                                <pagerange first="532" last="542"/>
                            </ref-volisspag>
                        </ref-info>
                        <ref-fulltext>Štrumbelj E, Vračar P (2012) Simulating a basketball match with a homogeneous Markov model and forecasting the outcome. Int J Forecast 28:532–542</ref-fulltext>
                    </reference>
                    <reference id="28">
                        <ref-info>
                            <ref-title>
                                <ref-titletext>Relative importance of performance factors in winning NBA games in regular season versus playoffs</ref-titletext>
                            </ref-title>
                            <refd-itemidlist>
                                <itemid idtype="FRAGMENTID">CR28</itemid>
                                <itemid idtype="SGR">84859841258</itemid>
                            </refd-itemidlist>
                            <ref-authors>
                                <author seq="1">
                                    <ce:initials>M.</ce:initials>
                                    <ce:indexed-name>Teramoto M.</ce:indexed-name>
                                    <ce:surname>Teramoto</ce:surname>
                                </author>
                                <author seq="2">
                                    <ce:initials>C.L.</ce:initials>
                                    <ce:indexed-name>Cross C.L.</ce:indexed-name>
                                    <ce:surname>Cross</ce:surname>
                                </author>
                            </ref-authors>
                            <ref-sourcetitle>J Quant Anal Sports</ref-sourcetitle>
                            <ref-publicationyear first="2010"/>
                            <ref-volisspag>
                                <voliss issue="3" volume="6"/>
                                <pagerange first="1" last="17"/>
                            </ref-volisspag>
                        </ref-info>
                        <ref-fulltext>Teramoto M, Cross CL (2010) Relative importance of performance factors in winning NBA games in regular season versus playoffs. J Quant Anal Sports 6(3):1–17</ref-fulltext>
                    </reference>
                    <reference id="29">
                        <ref-info>
                            <ref-title>
                                <ref-titletext>Modeling basketball play-by-play data</ref-titletext>
                            </ref-title>
                            <refd-itemidlist>
                                <itemid idtype="DOI">10.1016/j.eswa.2015.09.004</itemid>
                                <itemid idtype="FRAGMENTID">CR29</itemid>
                                <itemid idtype="SGR">84944218450</itemid>
                            </refd-itemidlist>
                            <ref-authors>
                                <author seq="1">
                                    <ce:initials>P.</ce:initials>
                                    <ce:indexed-name>Vracar P.</ce:indexed-name>
                                    <ce:surname>Vračar</ce:surname>
                                </author>
                                <author seq="2">
                                    <ce:initials>E.</ce:initials>
                                    <ce:indexed-name>Strumbelj E.</ce:indexed-name>
                                    <ce:surname>Štrumbelj</ce:surname>
                                </author>
                                <author seq="3">
                                    <ce:initials>I.</ce:initials>
                                    <ce:indexed-name>Kononenko I.</ce:indexed-name>
                                    <ce:surname>Kononenko</ce:surname>
                                </author>
                            </ref-authors>
                            <ref-sourcetitle>Expert Syst Appl</ref-sourcetitle>
                            <ref-publicationyear first="2016"/>
                            <ref-volisspag>
                                <voliss volume="44"/>
                                <pagerange first="58" last="66"/>
                            </ref-volisspag>
                        </ref-info>
                        <ref-fulltext>Vračar P, Štrumbelj E, Kononenko I (2016) Modeling basketball play-by-play data. Expert Syst Appl 44:58–66</ref-fulltext>
                    </reference>
                </bibliography></tail></bibrecord></item></abstracts-retrieval-response>